[
  {
    "title": "【台風6号】沖縄・奄美にあすから接近 九州～関東甲信で大雨も",
    "link": "http://www3.nhk.or.jp/news/html/20260531/k10015136211000.html",
    "source": "NHK",
    "image": ""
  },
  {
    "title": "小泉防衛相“高い透明性で防衛力強化” 中国の批判念頭に反論",
    "link": "http://www3.nhk.or.jp/news/html/20260531/k10015136301000.html",
    "source": "NHK",
    "image": ""
  },
  {
    "title": "【台風影響】沖縄発着便など あさってにかけ290便余欠航",
    "link": "http://www3.nhk.or.jp/news/html/20260531/k10015136311000.html",
    "source": "NHK",
    "image": ""
  },
  {
    "title": "中国 5月の製造業景況感の指数悪化 原油高が新たな懸念材料に",
    "link": "http://www3.nhk.or.jp/news/html/20260531/k10015136341000.html",
    "source": "NHK",
    "image": ""
  },
  {
    "title": "医療や福祉の「ケア労働者」対象に全国で電話相談会 全労連",
    "link": "http://www3.nhk.or.jp/news/html/20260531/k10015136351000.html",
    "source": "NHK",
    "image": ""
  },
  {
    "title": "イラン核協議の覚書 “トランプ大統領が修正要求”米報道",
    "link": "http://www3.nhk.or.jp/news/html/20260531/k10015136361000.html",
    "source": "NHK",
    "image": ""
  },
  {
    "title": "名古屋 マイクロバス事故 現場にブレーキかけた痕跡なし",
    "link": "http://www3.nhk.or.jp/news/html/20260531/k10015136371000.html",
    "source": "NHK",
    "image": ""
  }
]
