[
  {
    "title": "中央道 バス炎上で乗客40人避難 エンジントラブルか 東京 日野",
    "link": "http://www3.nhk.or.jp/news/html/20260218/k10015054831000.html",
    "source": "NHK",
    "image": ""
  },
  {
    "title": "特別国会召集 午後首相指名選挙 第2次高市内閣発足へ",
    "link": "http://www3.nhk.or.jp/news/html/20260218/k10015054851000.html",
    "source": "NHK",
    "image": ""
  },
  {
    "title": "政府 対米投資の第1弾発表 赤澤経産相 “双方にメリット”強調",
    "link": "http://www3.nhk.or.jp/news/html/20260218/k10015054891000.html",
    "source": "NHK",
    "image": ""
  },
  {
    "title": "スキージャンプ女子でメダル獲得 丸山希と高梨沙羅が帰国 五輪",
    "link": "http://www3.nhk.or.jp/news/html/20260218/k10015054901000.html",
    "source": "NHK",
    "image": ""
  },
  {
    "title": "札幌 白石区で落雪 雪の中から3人救助も男性1人意識なし",
    "link": "http://www3.nhk.or.jp/news/html/20260218/k10015054921000.html",
    "source": "NHK",
    "image": ""
  },
  {
    "title": "航空機内でモバイルバッテリーの使用禁止へ 4月から 国交省",
    "link": "http://www3.nhk.or.jp/news/html/20260218/k10015054951000.html",
    "source": "NHK",
    "image": ""
  },
  {
    "title": "東広島 男性殺人事件「灯油か何かをまかれて火をつけられた」",
    "link": "http://www3.nhk.or.jp/news/html/20260218/k10015054991000.html",
    "source": "NHK",
    "image": ""
  }
]
