[
  {
    "title": "衆議院選挙あす公示 高市政権の政策の是非など争点に選挙戦へ",
    "link": "http://www3.nhk.or.jp/news/html/20260126/k10015035491000.html",
    "source": "NHK",
    "image": ""
  },
  {
    "title": "日本海側で平年を大幅に上回る積雪 交通影響などに十分注意を",
    "link": "http://www3.nhk.or.jp/news/html/20260126/k10015035521000.html",
    "source": "NHK",
    "image": ""
  },
  {
    "title": "青森 スノーモービル乗るため入山の8人 全員の無事を確認",
    "link": "http://www3.nhk.or.jp/news/html/20260126/k10015035571000.html",
    "source": "NHK",
    "image": ""
  },
  {
    "title": "北海道 記録的な大雪で多くの列車が運休 新千歳空港で足止めも",
    "link": "http://www3.nhk.or.jp/news/html/20260126/k10015035581000.html",
    "source": "NHK",
    "image": ""
  },
  {
    "title": "トランプ大統領 アフガン派兵めぐる発言を事実上撤回",
    "link": "http://www3.nhk.or.jp/news/html/20260126/k10015035591000.html",
    "source": "NHK",
    "image": ""
  },
  {
    "title": "円高ドル安急速に進む 株価 一時1000円超の値下がり",
    "link": "http://www3.nhk.or.jp/news/html/20260126/k10015035651000.html",
    "source": "NHK",
    "image": ""
  },
  {
    "title": "東京電力HD 今後10年間の新たな再建計画 国が認定",
    "link": "http://www3.nhk.or.jp/news/html/20260126/k10015035661000.html",
    "source": "NHK",
    "image": ""
  }
]
