[
  {
    "title": "奈良の「飛鳥・藤原の宮都」世界文化遺産に登録される見通しに",
    "link": "http://www3.nhk.or.jp/news/html/20260606/k10015142291000.html",
    "source": "NHK",
    "image": ""
  },
  {
    "title": "トランプ大統領 再び軍事力行使示唆 イランは無人機発射か",
    "link": "http://www3.nhk.or.jp/news/html/20260606/k10015142611000.html",
    "source": "NHK",
    "image": ""
  },
  {
    "title": "パスポート申請手数料減額へ 7月以降は申請大幅増の予想",
    "link": "http://www3.nhk.or.jp/news/html/20260606/k10015142741000.html",
    "source": "NHK",
    "image": ""
  },
  {
    "title": "北海道 函館で住宅火災 2人死亡 本別町でも1人死亡の火事",
    "link": "http://www3.nhk.or.jp/news/html/20260606/k10015142771000.html",
    "source": "NHK",
    "image": ""
  },
  {
    "title": "サッカーW杯日本代表 非公開練習でセットプレーの対応など確認",
    "link": "http://www3.nhk.or.jp/news/html/20260606/k10015142781000.html",
    "source": "NHK",
    "image": ""
  },
  {
    "title": "北朝鮮 キム総書記 “海軍を核戦争の抑止力の一翼へ強化”",
    "link": "http://www3.nhk.or.jp/news/html/20260606/k10015142801000.html",
    "source": "NHK",
    "image": ""
  },
  {
    "title": "低気圧と前線で非常に激しい雨 奄美地方で土砂災害危険警報も",
    "link": "http://www3.nhk.or.jp/news/html/20260606/k10015142821000.html",
    "source": "NHK",
    "image": ""
  }
]
