[
  {
    "title": "安保3文書改定 防衛費の規模や非核三原則扱いが焦点に",
    "link": "http://www3.nhk.or.jp/news/html/20260625/k10015158711000.html",
    "source": "NHK",
    "image": ""
  },
  {
    "title": "九州北部で非常に激しい雨 昼前にかけ線状降水帯発生おそれ",
    "link": "http://www3.nhk.or.jp/news/html/20260625/k10015158771000.html",
    "source": "NHK",
    "image": ""
  },
  {
    "title": "アメリカとイランの実務協議 30日にも再開か",
    "link": "http://www3.nhk.or.jp/news/html/20260625/k10015158781000.html",
    "source": "NHK",
    "image": ""
  },
  {
    "title": "神戸 冷凍庫遺体遺棄事件 元妻「電気代去年ごろまで払う」供述",
    "link": "http://www3.nhk.or.jp/news/html/20260625/k10015158821000.html",
    "source": "NHK",
    "image": ""
  },
  {
    "title": "教育基本法改正20年 かつての与党協議の議事録を入手",
    "link": "http://www3.nhk.or.jp/news/html/20260625/k10015158881000.html",
    "source": "NHK",
    "image": ""
  },
  {
    "title": "ペルー大統領選挙 フジモリ元大統領の長女ケイコ氏が優勢",
    "link": "http://www3.nhk.or.jp/news/html/20260625/k10015158911000.html",
    "source": "NHK",
    "image": ""
  },
  {
    "title": "サッカーW杯 ボスニア・ヘルツェゴビナが勝利しグループ3位に",
    "link": "http://www3.nhk.or.jp/news/html/20260625/k10015158951000.html",
    "source": "NHK",
    "image": ""
  }
]
