[
  {
    "title": "JR山手線の停電トラブル 67万人余に影響 感電防止装置に不具合",
    "link": "http://www3.nhk.or.jp/news/html/20260116/k10015027701000.html",
    "source": "NHK",
    "image": ""
  },
  {
    "title": "立民・公明の新党 名称は「中道改革連合」に",
    "link": "http://www3.nhk.or.jp/news/html/20260116/k10015027771000.html",
    "source": "NHK",
    "image": ""
  },
  {
    "title": "阪神・淡路大震災から17日で31年 神戸で追悼のつどい始まる",
    "link": "http://www3.nhk.or.jp/news/html/20260116/k10015027871000.html",
    "source": "NHK",
    "image": ""
  },
  {
    "title": "iPS細胞を使うがん治療の治験 “一定の有効性確認” 国内で初",
    "link": "http://www3.nhk.or.jp/news/html/20260116/k10015028411000.html",
    "source": "NHK",
    "image": ""
  },
  {
    "title": "山梨 山林火災 大月市が138世帯に新たに避難指示",
    "link": "http://www3.nhk.or.jp/news/html/20260116/k10015028471000.html",
    "source": "NHK",
    "image": ""
  },
  {
    "title": "衆院選へ急ピッチで準備進む 真冬・受験シーズンで懸念も…",
    "link": "http://www3.nhk.or.jp/news/html/20260116/k10015028501000.html",
    "source": "NHK",
    "image": ""
  },
  {
    "title": "高市首相 19日夕方に記者会見 解散に踏み切る理由など説明へ",
    "link": "http://www3.nhk.or.jp/news/html/20260116/k10015028681000.html",
    "source": "NHK",
    "image": ""
  }
]
