[
  {
    "title": "7年後 支える側になれた“りくりゅう”年下の三浦璃来【解説】",
    "link": "http://www3.nhk.or.jp/news/html/20260217/k10015053721000.html",
    "source": "NHK",
    "image": ""
  },
  {
    "title": "花粉の飛散予測 平年の約1.3倍に 2月下旬から飛散エリア拡大か",
    "link": "http://www3.nhk.or.jp/news/html/20260217/k10015054011000.html",
    "source": "NHK",
    "image": ""
  },
  {
    "title": "JR東日本 宇都宮線の架線断線“人為的ミスで別架線張り替え”",
    "link": "http://www3.nhk.or.jp/news/html/20260217/k10015054391000.html",
    "source": "NHK",
    "image": ""
  },
  {
    "title": "東広島 男性死亡事件 首の傷は複数確認 死因は失血死",
    "link": "http://www3.nhk.or.jp/news/html/20260217/k10015054431000.html",
    "source": "NHK",
    "image": ""
  },
  {
    "title": "ノルディック複合 個人ラージヒル 山本涼太 前半ジャンプ1位",
    "link": "http://www3.nhk.or.jp/news/html/20260217/k10015054481000.html",
    "source": "NHK",
    "image": ""
  },
  {
    "title": "スノーボード女子スロープスタイル 決勝 天候不良のため延期",
    "link": "http://www3.nhk.or.jp/news/html/20260217/k10015054501000.html",
    "source": "NHK",
    "image": ""
  },
  {
    "title": "横浜 鶴見区 住宅火事 5棟燃える 1人けが",
    "link": "http://www3.nhk.or.jp/news/html/20260217/k10015054561000.html",
    "source": "NHK",
    "image": ""
  }
]
