[
  {
    "title": "トランプ大統領 イランとの停戦や覚書「終わったと思う」",
    "link": "http://www3.nhk.or.jp/news/html/20260708/k10015171371000.html",
    "source": "NHK",
    "image": ""
  },
  {
    "title": "茨城 同居女性の唇縫い付け事件 被害女性 食事とれない状態",
    "link": "http://www3.nhk.or.jp/news/html/20260708/k10015171551000.html",
    "source": "NHK",
    "image": ""
  },
  {
    "title": "九州北部 中国地方 近畿で梅雨明け 9日はさらに気温上昇",
    "link": "http://www3.nhk.or.jp/news/html/20260708/k10015171561000.html",
    "source": "NHK",
    "image": ""
  },
  {
    "title": "コメめぐり「需要に応じた生産」明記の改正食糧法が成立",
    "link": "http://www3.nhk.or.jp/news/html/20260708/k10015171601000.html",
    "source": "NHK",
    "image": ""
  },
  {
    "title": "高齢ドライバーの「運転技能検査」 見直し検討始める 警察庁",
    "link": "http://www3.nhk.or.jp/news/html/20260708/k10015172041000.html",
    "source": "NHK",
    "image": ""
  },
  {
    "title": "円相場 値下がり アメリカとイランの緊張の高まり受け",
    "link": "http://www3.nhk.or.jp/news/html/20260708/k10015172121000.html",
    "source": "NHK",
    "image": ""
  },
  {
    "title": "サッカー 三笘薫選手 車を運転中に自転車と衝突 女性けが",
    "link": "http://www3.nhk.or.jp/news/html/20260708/k10015172141000.html",
    "source": "NHK",
    "image": ""
  }
]
