[
  {
    "title": "福岡 太宰府で38度 20日も埼玉で危険な暑さ予想 熱中症対策を",
    "link": "http://www3.nhk.or.jp/news/html/20260719/k10015180531000.html",
    "source": "NHK",
    "image": ""
  },
  {
    "title": "W杯 チケット価格高騰 試合直前 決勝は最低価格でも超高額",
    "link": "http://www3.nhk.or.jp/news/html/20260719/k10015180701000.html",
    "source": "NHK",
    "image": ""
  },
  {
    "title": "【速報中】決勝 スペイン×アルゼンチン 無得点で後半も終盤",
    "link": "http://www3.nhk.or.jp/news/html/20260720/k10015180471000.html",
    "source": "NHK",
    "image": ""
  },
  {
    "title": "富山 黒部 沖合に流された小学4年生が死亡",
    "link": "http://www3.nhk.or.jp/news/html/20260720/k10015180981000.html",
    "source": "NHK",
    "image": ""
  },
  {
    "title": "メッシと赤ちゃん時代のヤマル 撮影の舞台裏は ユニセフ",
    "link": "http://www3.nhk.or.jp/news/html/20260720/k10015180991000.html",
    "source": "NHK",
    "image": ""
  },
  {
    "title": "ロシアがウクライナに弾道ミサイルで攻撃 過去最大規模か",
    "link": "http://www3.nhk.or.jp/news/html/20260720/k10015181001000.html",
    "source": "NHK",
    "image": ""
  },
  {
    "title": "奈良 西名阪道で逆走か 軽乗用車どうしが正面衝突 2人死亡",
    "link": "http://www3.nhk.or.jp/news/html/20260720/k10015181011000.html",
    "source": "NHK",
    "image": ""
  }
]
